decaf/__init__.py
decaf/decaf.py
decaf/io.py
decaf/ocean.py
decaf/siteconfig.py
decaf/utils.py
decaf/validate.py
decaf_espresso-0.3.1.dist-info/METADATA
decaf_espresso-0.3.1.dist-info/RECORD
decaf_espresso-0.3.1.dist-info/WHEEL
decaf_espresso-0.3.1.dist-info/top_level.txt
