Metadata-Version: 2.1
Name: decaf-espresso
Version: 0.3.1
Summary: Light-weight ASE calculator wrapper for Quantum Espresso.
Home-page: https://github.com/jboes/decaf-espresso
Author: Jacob Boes
Author-email: jacobboes@gmail.com
License: GPL-3.0
Platform: UNKNOWN
Classifier: Development Status :: 4 - Beta
Classifier: Intended Audience :: Developers
Classifier: Topic :: Scientific/Engineering :: Chemistry
Classifier: License :: OSI Approved :: GNU General Public License v3 (GPLv3)
Classifier: Programming Language :: Python
Classifier: Programming Language :: Python :: 2
Classifier: Programming Language :: Python :: 2.7
Classifier: Programming Language :: Python :: 3
Classifier: Programming Language :: Python :: 3.5
Classifier: Programming Language :: Python :: 3.6
Requires-Python: >=2.7, !=3.0.*, !=3.1.*, !=3.2.*, !=3.3.*, !=3.4.*, <4
Requires-Dist: ase (>=3.16)
Requires-Dist: numpy (>=1.14)
Requires-Dist: path.py (>=11.0.1)
